{
  "annotations": {
    "list": [
      {
        "builtIn": 1,
        "datasource": { "type": "grafana", "uid": "-- Grafana --" },
        "enable": true,
        "hide": true,
        "iconColor": "rgba(0, 211, 255, 1)",
        "name": "Annotations & Alerts",
        "type": "dashboard"
      }
    ]
  },
  "editable": true,
  "fiscalYearStartMonth": 0,
  "graphTooltip": 1,
  "id": null,
  "links": [],
  "panels": [
    {
      "collapsed": false,
      "gridPos": { "h": 1, "w": 24, "x": 0, "y": 0 },
      "id": 1,
      "title": "API Performance",
      "type": "row"
    },
    {
      "datasource": { "type": "prometheus", "uid": "${DS_PROMETHEUS}" },
      "description": "HTTP requests per second across all endpoints",
      "fieldConfig": {
        "defaults": {
          "color": { "mode": "palette-classic" },
          "custom": {
            "axisBorderShow": false,
            "axisCenteredZero": false,
            "axisLabel": "req/s",
            "axisPlacement": "auto",
            "barAlignment": 0,
            "drawStyle": "line",
            "fillOpacity": 15,
            "gradientMode": "none",
            "hideFrom": { "legend": false, "tooltip": false, "viz": false },
            "insertNulls": false,
            "lineInterpolation": "smooth",
            "lineWidth": 2,
            "pointSize": 5,
            "scaleDistribution": { "type": "linear" },
            "showPoints": "never",
            "spanNulls": false,
            "stacking": { "group": "A", "mode": "none" },
            "thresholdsStyle": { "mode": "off" }
          },
          "mappings": [],
          "thresholds": {
            "mode": "absolute",
            "steps": [
              { "color": "green", "value": null }
            ]
          },
          "unit": "reqps"
        },
        "overrides": []
      },
      "gridPos": { "h": 8, "w": 6, "x": 0, "y": 1 },
      "id": 2,
      "options": {
        "legend": { "calcs": ["mean", "max"], "displayMode": "table", "placement": "bottom" },
        "tooltip": { "mode": "multi", "sort": "desc" }
      },
      "targets": [
        {
          "datasource": { "type": "prometheus", "uid": "${DS_PROMETHEUS}" },
          "editorMode": "code",
          "expr": "sum(rate(agledger_http_request_duration_seconds_count[5m]))",
          "legendFormat": "Total Request Rate",
          "range": true,
          "refId": "A"
        },
        {
          "datasource": { "type": "prometheus", "uid": "${DS_PROMETHEUS}" },
          "editorMode": "code",
          "expr": "sum by (method) (rate(agledger_http_request_duration_seconds_count[5m]))",
          "legendFormat": "{{ method }}",
          "range": true,
          "refId": "B"
        }
      ],
      "title": "HTTP Request Rate",
      "type": "timeseries"
    },
    {
      "datasource": { "type": "prometheus", "uid": "${DS_PROMETHEUS}" },
      "description": "95th percentile HTTP request duration",
      "fieldConfig": {
        "defaults": {
          "color": { "mode": "palette-classic" },
          "custom": {
            "axisBorderShow": false,
            "axisCenteredZero": false,
            "axisLabel": "",
            "axisPlacement": "auto",
            "barAlignment": 0,
            "drawStyle": "line",
            "fillOpacity": 10,
            "gradientMode": "none",
            "hideFrom": { "legend": false, "tooltip": false, "viz": false },
            "insertNulls": false,
            "lineInterpolation": "smooth",
            "lineWidth": 2,
            "pointSize": 5,
            "scaleDistribution": { "type": "linear" },
            "showPoints": "never",
            "spanNulls": false,
            "stacking": { "group": "A", "mode": "none" },
            "thresholdsStyle": { "mode": "line+area" }
          },
          "mappings": [],
          "thresholds": {
            "mode": "absolute",
            "steps": [
              { "color": "green", "value": null },
              { "color": "yellow", "value": 0.5 },
              { "color": "red", "value": 1.0 }
            ]
          },
          "unit": "s"
        },
        "overrides": []
      },
      "gridPos": { "h": 8, "w": 6, "x": 6, "y": 1 },
      "id": 3,
      "options": {
        "legend": { "calcs": ["mean", "max"], "displayMode": "table", "placement": "bottom" },
        "tooltip": { "mode": "multi", "sort": "desc" }
      },
      "targets": [
        {
          "datasource": { "type": "prometheus", "uid": "${DS_PROMETHEUS}" },
          "editorMode": "code",
          "expr": "histogram_quantile(0.95, sum by (le) (rate(agledger_http_request_duration_seconds_bucket[5m])))",
          "legendFormat": "P95 Overall",
          "range": true,
          "refId": "A"
        },
        {
          "datasource": { "type": "prometheus", "uid": "${DS_PROMETHEUS}" },
          "editorMode": "code",
          "expr": "histogram_quantile(0.95, sum by (le, route) (rate(agledger_http_request_duration_seconds_bucket[5m])))",
          "legendFormat": "P95 {{ route }}",
          "range": true,
          "refId": "B"
        }
      ],
      "title": "HTTP Request Duration P95",
      "type": "timeseries"
    },
    {
      "datasource": { "type": "prometheus", "uid": "${DS_PROMETHEUS}" },
      "description": "Rate of 4xx and 5xx HTTP responses",
      "fieldConfig": {
        "defaults": {
          "color": { "mode": "palette-classic" },
          "custom": {
            "axisBorderShow": false,
            "axisCenteredZero": false,
            "axisLabel": "errors/s",
            "axisPlacement": "auto",
            "barAlignment": 0,
            "drawStyle": "line",
            "fillOpacity": 20,
            "gradientMode": "none",
            "hideFrom": { "legend": false, "tooltip": false, "viz": false },
            "insertNulls": false,
            "lineInterpolation": "smooth",
            "lineWidth": 2,
            "pointSize": 5,
            "scaleDistribution": { "type": "linear" },
            "showPoints": "never",
            "spanNulls": false,
            "stacking": { "group": "A", "mode": "normal" },
            "thresholdsStyle": { "mode": "off" }
          },
          "mappings": [],
          "thresholds": {
            "mode": "absolute",
            "steps": [
              { "color": "green", "value": null }
            ]
          },
          "unit": "reqps"
        },
        "overrides": [
          {
            "matcher": { "id": "byName", "options": "4xx" },
            "properties": [
              { "id": "color", "value": { "fixedColor": "yellow", "mode": "fixed" } }
            ]
          },
          {
            "matcher": { "id": "byName", "options": "5xx" },
            "properties": [
              { "id": "color", "value": { "fixedColor": "red", "mode": "fixed" } }
            ]
          }
        ]
      },
      "gridPos": { "h": 8, "w": 6, "x": 12, "y": 1 },
      "id": 4,
      "options": {
        "legend": { "calcs": ["mean", "max"], "displayMode": "table", "placement": "bottom" },
        "tooltip": { "mode": "multi", "sort": "desc" }
      },
      "targets": [
        {
          "datasource": { "type": "prometheus", "uid": "${DS_PROMETHEUS}" },
          "editorMode": "code",
          "expr": "sum(rate(agledger_http_request_duration_seconds_count{status_code=~\"4..\"}[5m]))",
          "legendFormat": "4xx",
          "range": true,
          "refId": "A"
        },
        {
          "datasource": { "type": "prometheus", "uid": "${DS_PROMETHEUS}" },
          "editorMode": "code",
          "expr": "sum(rate(agledger_http_request_duration_seconds_count{status_code=~\"5..\"}[5m]))",
          "legendFormat": "5xx",
          "range": true,
          "refId": "B"
        }
      ],
      "title": "HTTP Error Rate",
      "type": "timeseries"
    },
    {
      "datasource": { "type": "prometheus", "uid": "${DS_PROMETHEUS}" },
      "description": "Currently active HTTP requests being processed",
      "fieldConfig": {
        "defaults": {
          "color": {
            "mode": "thresholds"
          },
          "mappings": [],
          "thresholds": {
            "mode": "absolute",
            "steps": [
              { "color": "green", "value": null },
              { "color": "yellow", "value": 50 },
              { "color": "red", "value": 100 }
            ]
          },
          "unit": "none"
        },
        "overrides": []
      },
      "gridPos": { "h": 8, "w": 6, "x": 18, "y": 1 },
      "id": 5,
      "options": {
        "colorMode": "background_solid",
        "graphMode": "area",
        "justifyMode": "auto",
        "orientation": "auto",
        "percentChangeColorMode": "standard",
        "reduceOptions": {
          "calcs": ["lastNotNull"],
          "fields": "",
          "values": false
        },
        "showPercentChange": false,
        "textMode": "auto",
        "wideLayout": true
      },
      "targets": [
        {
          "datasource": { "type": "prometheus", "uid": "${DS_PROMETHEUS}" },
          "editorMode": "code",
          "expr": "agledger_http_active_requests",
          "legendFormat": "Active Requests",
          "range": true,
          "refId": "A"
        }
      ],
      "title": "Active Requests",
      "type": "stat"
    },
    {
      "collapsed": false,
      "gridPos": { "h": 1, "w": 24, "x": 0, "y": 9 },
      "id": 10,
      "title": "Mandate Operations",
      "type": "row"
    },
    {
      "datasource": { "type": "prometheus", "uid": "${DS_PROMETHEUS}" },
      "description": "Rate of mandate state transitions broken down by target status",
      "fieldConfig": {
        "defaults": {
          "color": { "mode": "palette-classic" },
          "custom": {
            "axisBorderShow": false,
            "axisCenteredZero": false,
            "axisLabel": "transitions/s",
            "axisPlacement": "auto",
            "barAlignment": 0,
            "drawStyle": "line",
            "fillOpacity": 15,
            "gradientMode": "none",
            "hideFrom": { "legend": false, "tooltip": false, "viz": false },
            "insertNulls": false,
            "lineInterpolation": "smooth",
            "lineWidth": 2,
            "pointSize": 5,
            "scaleDistribution": { "type": "linear" },
            "showPoints": "never",
            "spanNulls": false,
            "stacking": { "group": "A", "mode": "none" },
            "thresholdsStyle": { "mode": "off" }
          },
          "mappings": [],
          "thresholds": {
            "mode": "absolute",
            "steps": [
              { "color": "green", "value": null }
            ]
          },
          "unit": "ops"
        },
        "overrides": []
      },
      "gridPos": { "h": 8, "w": 8, "x": 0, "y": 10 },
      "id": 11,
      "options": {
        "legend": { "calcs": ["mean", "max"], "displayMode": "table", "placement": "bottom" },
        "tooltip": { "mode": "multi", "sort": "desc" }
      },
      "targets": [
        {
          "datasource": { "type": "prometheus", "uid": "${DS_PROMETHEUS}" },
          "editorMode": "code",
          "expr": "sum by (to_status) (rate(agledger_mandate_transitions_total[5m]))",
          "legendFormat": "{{ to_status }}",
          "range": true,
          "refId": "A"
        }
      ],
      "title": "Mandate Transitions Rate",
      "type": "timeseries"
    },
    {
      "datasource": { "type": "prometheus", "uid": "${DS_PROMETHEUS}" },
      "description": "95th percentile verification duration",
      "fieldConfig": {
        "defaults": {
          "color": { "mode": "palette-classic" },
          "custom": {
            "axisBorderShow": false,
            "axisCenteredZero": false,
            "axisLabel": "",
            "axisPlacement": "auto",
            "barAlignment": 0,
            "drawStyle": "line",
            "fillOpacity": 10,
            "gradientMode": "none",
            "hideFrom": { "legend": false, "tooltip": false, "viz": false },
            "insertNulls": false,
            "lineInterpolation": "smooth",
            "lineWidth": 2,
            "pointSize": 5,
            "scaleDistribution": { "type": "linear" },
            "showPoints": "never",
            "spanNulls": false,
            "stacking": { "group": "A", "mode": "none" },
            "thresholdsStyle": { "mode": "line+area" }
          },
          "mappings": [],
          "thresholds": {
            "mode": "absolute",
            "steps": [
              { "color": "green", "value": null },
              { "color": "yellow", "value": 2 },
              { "color": "red", "value": 5 }
            ]
          },
          "unit": "s"
        },
        "overrides": []
      },
      "gridPos": { "h": 8, "w": 8, "x": 8, "y": 10 },
      "id": 12,
      "options": {
        "legend": { "calcs": ["mean", "max"], "displayMode": "table", "placement": "bottom" },
        "tooltip": { "mode": "multi", "sort": "desc" }
      },
      "targets": [
        {
          "datasource": { "type": "prometheus", "uid": "${DS_PROMETHEUS}" },
          "editorMode": "code",
          "expr": "histogram_quantile(0.95, sum by (le) (rate(agledger_verification_duration_seconds_bucket[5m])))",
          "legendFormat": "P95 Verification",
          "range": true,
          "refId": "A"
        },
        {
          "datasource": { "type": "prometheus", "uid": "${DS_PROMETHEUS}" },
          "editorMode": "code",
          "expr": "histogram_quantile(0.50, sum by (le) (rate(agledger_verification_duration_seconds_bucket[5m])))",
          "legendFormat": "P50 Verification",
          "range": true,
          "refId": "B"
        }
      ],
      "title": "Verification Duration P95",
      "type": "timeseries"
    },
    {
      "datasource": { "type": "prometheus", "uid": "${DS_PROMETHEUS}" },
      "description": "Worker job processing rate by queue and status",
      "fieldConfig": {
        "defaults": {
          "color": { "mode": "palette-classic" },
          "custom": {
            "axisBorderShow": false,
            "axisCenteredZero": false,
            "axisLabel": "jobs/s",
            "axisPlacement": "auto",
            "barAlignment": 0,
            "drawStyle": "line",
            "fillOpacity": 15,
            "gradientMode": "none",
            "hideFrom": { "legend": false, "tooltip": false, "viz": false },
            "insertNulls": false,
            "lineInterpolation": "smooth",
            "lineWidth": 2,
            "pointSize": 5,
            "scaleDistribution": { "type": "linear" },
            "showPoints": "never",
            "spanNulls": false,
            "stacking": { "group": "A", "mode": "none" },
            "thresholdsStyle": { "mode": "off" }
          },
          "mappings": [],
          "thresholds": {
            "mode": "absolute",
            "steps": [
              { "color": "green", "value": null }
            ]
          },
          "unit": "ops"
        },
        "overrides": [
          {
            "matcher": { "id": "byRegexp", "options": ".*failed.*" },
            "properties": [
              { "id": "color", "value": { "fixedColor": "red", "mode": "fixed" } }
            ]
          }
        ]
      },
      "gridPos": { "h": 8, "w": 8, "x": 16, "y": 10 },
      "id": 13,
      "options": {
        "legend": { "calcs": ["mean", "max"], "displayMode": "table", "placement": "bottom" },
        "tooltip": { "mode": "multi", "sort": "desc" }
      },
      "targets": [
        {
          "datasource": { "type": "prometheus", "uid": "${DS_PROMETHEUS}" },
          "editorMode": "code",
          "expr": "sum by (queue, status) (rate(agledger_worker_jobs_processed_total[5m]))",
          "legendFormat": "{{ queue }} ({{ status }})",
          "range": true,
          "refId": "A"
        }
      ],
      "title": "Worker Jobs Processed",
      "type": "timeseries"
    },
    {
      "collapsed": false,
      "gridPos": { "h": 1, "w": 24, "x": 0, "y": 18 },
      "id": 20,
      "title": "Infrastructure",
      "type": "row"
    },
    {
      "datasource": { "type": "prometheus", "uid": "${DS_PROMETHEUS}" },
      "description": "PostgreSQL connection pool status",
      "fieldConfig": {
        "defaults": {
          "color": { "mode": "palette-classic" },
          "custom": {
            "axisBorderShow": false,
            "axisCenteredZero": false,
            "axisLabel": "connections",
            "axisPlacement": "auto",
            "barAlignment": 0,
            "drawStyle": "line",
            "fillOpacity": 10,
            "gradientMode": "none",
            "hideFrom": { "legend": false, "tooltip": false, "viz": false },
            "insertNulls": false,
            "lineInterpolation": "smooth",
            "lineWidth": 2,
            "pointSize": 5,
            "scaleDistribution": { "type": "linear" },
            "showPoints": "never",
            "spanNulls": false,
            "stacking": { "group": "A", "mode": "none" },
            "thresholdsStyle": { "mode": "off" }
          },
          "mappings": [],
          "thresholds": {
            "mode": "absolute",
            "steps": [
              { "color": "green", "value": null }
            ]
          },
          "unit": "none"
        },
        "overrides": [
          {
            "matcher": { "id": "byName", "options": "Total" },
            "properties": [
              { "id": "color", "value": { "fixedColor": "blue", "mode": "fixed" } }
            ]
          },
          {
            "matcher": { "id": "byName", "options": "Idle" },
            "properties": [
              { "id": "color", "value": { "fixedColor": "green", "mode": "fixed" } }
            ]
          },
          {
            "matcher": { "id": "byName", "options": "Waiting" },
            "properties": [
              { "id": "color", "value": { "fixedColor": "orange", "mode": "fixed" } }
            ]
          }
        ]
      },
      "gridPos": { "h": 8, "w": 6, "x": 0, "y": 19 },
      "id": 21,
      "options": {
        "legend": { "calcs": ["lastNotNull"], "displayMode": "table", "placement": "bottom" },
        "tooltip": { "mode": "multi", "sort": "desc" }
      },
      "targets": [
        {
          "datasource": { "type": "prometheus", "uid": "${DS_PROMETHEUS}" },
          "editorMode": "code",
          "expr": "agledger_db_pool_total_connections",
          "legendFormat": "Total",
          "range": true,
          "refId": "A"
        },
        {
          "datasource": { "type": "prometheus", "uid": "${DS_PROMETHEUS}" },
          "editorMode": "code",
          "expr": "agledger_db_pool_idle_connections",
          "legendFormat": "Idle",
          "range": true,
          "refId": "B"
        },
        {
          "datasource": { "type": "prometheus", "uid": "${DS_PROMETHEUS}" },
          "editorMode": "code",
          "expr": "agledger_db_pool_waiting_connections",
          "legendFormat": "Waiting",
          "range": true,
          "refId": "C"
        }
      ],
      "title": "DB Pool Connections",
      "type": "timeseries"
    },
    {
      "datasource": { "type": "prometheus", "uid": "${DS_PROMETHEUS}" },
      "description": "Process resident set size (RSS) memory usage",
      "fieldConfig": {
        "defaults": {
          "color": { "mode": "palette-classic" },
          "custom": {
            "axisBorderShow": false,
            "axisCenteredZero": false,
            "axisLabel": "",
            "axisPlacement": "auto",
            "barAlignment": 0,
            "drawStyle": "line",
            "fillOpacity": 20,
            "gradientMode": "scheme",
            "hideFrom": { "legend": false, "tooltip": false, "viz": false },
            "insertNulls": false,
            "lineInterpolation": "smooth",
            "lineWidth": 2,
            "pointSize": 5,
            "scaleDistribution": { "type": "linear" },
            "showPoints": "never",
            "spanNulls": false,
            "stacking": { "group": "A", "mode": "none" },
            "thresholdsStyle": { "mode": "line+area" }
          },
          "mappings": [],
          "thresholds": {
            "mode": "absolute",
            "steps": [
              { "color": "green", "value": null },
              { "color": "yellow", "value": 1073741824 },
              { "color": "red", "value": 1610612736 }
            ]
          },
          "unit": "bytes"
        },
        "overrides": []
      },
      "gridPos": { "h": 8, "w": 6, "x": 12, "y": 19 },
      "id": 23,
      "options": {
        "legend": { "calcs": ["mean", "max"], "displayMode": "table", "placement": "bottom" },
        "tooltip": { "mode": "multi", "sort": "desc" }
      },
      "targets": [
        {
          "datasource": { "type": "prometheus", "uid": "${DS_PROMETHEUS}" },
          "editorMode": "code",
          "expr": "agledger_process_resident_memory_bytes",
          "legendFormat": "RSS Memory",
          "range": true,
          "refId": "A"
        }
      ],
      "title": "Process Memory",
      "type": "timeseries"
    },
    {
      "datasource": { "type": "prometheus", "uid": "${DS_PROMETHEUS}" },
      "description": "Process CPU usage rate",
      "fieldConfig": {
        "defaults": {
          "color": { "mode": "palette-classic" },
          "custom": {
            "axisBorderShow": false,
            "axisCenteredZero": false,
            "axisLabel": "CPU cores",
            "axisPlacement": "auto",
            "barAlignment": 0,
            "drawStyle": "line",
            "fillOpacity": 20,
            "gradientMode": "scheme",
            "hideFrom": { "legend": false, "tooltip": false, "viz": false },
            "insertNulls": false,
            "lineInterpolation": "smooth",
            "lineWidth": 2,
            "pointSize": 5,
            "scaleDistribution": { "type": "linear" },
            "showPoints": "never",
            "spanNulls": false,
            "stacking": { "group": "A", "mode": "none" },
            "thresholdsStyle": { "mode": "line+area" }
          },
          "mappings": [],
          "thresholds": {
            "mode": "absolute",
            "steps": [
              { "color": "green", "value": null },
              { "color": "yellow", "value": 0.7 },
              { "color": "red", "value": 0.9 }
            ]
          },
          "unit": "none"
        },
        "overrides": []
      },
      "gridPos": { "h": 8, "w": 6, "x": 18, "y": 19 },
      "id": 24,
      "options": {
        "legend": { "calcs": ["mean", "max"], "displayMode": "table", "placement": "bottom" },
        "tooltip": { "mode": "multi", "sort": "desc" }
      },
      "targets": [
        {
          "datasource": { "type": "prometheus", "uid": "${DS_PROMETHEUS}" },
          "editorMode": "code",
          "expr": "rate(agledger_process_cpu_seconds_total[5m])",
          "legendFormat": "CPU Usage",
          "range": true,
          "refId": "A"
        }
      ],
      "title": "Process CPU",
      "type": "timeseries"
    }
  ],
  "schemaVersion": 39,
  "tags": ["agledger"],
  "templating": {
    "list": [
      {
        "current": {
          "selected": false,
          "text": "Prometheus",
          "value": "Prometheus"
        },
        "hide": 0,
        "includeAll": false,
        "multi": false,
        "name": "DS_PROMETHEUS",
        "options": [],
        "query": "prometheus",
        "queryValue": "",
        "refresh": 1,
        "regex": "",
        "skipUrlSync": false,
        "type": "datasource"
      }
    ]
  },
  "time": {
    "from": "now-1h",
    "to": "now"
  },
  "timepicker": {},
  "timezone": "browser",
  "title": "AGLedger Overview",
  "uid": "agledger-overview",
  "version": 1,
  "refresh": "30s"
}
